unknown_fields/__init__.py
unknown_fields/actions.py
unknown_fields/wrapper.py
unknown_fields-0.0.1a1.dist-info/LICENSE
unknown_fields-0.0.1a1.dist-info/METADATA
unknown_fields-0.0.1a1.dist-info/WHEEL
unknown_fields-0.0.1a1.dist-info/top_level.txt
unknown_fields-0.0.1a1.dist-info/RECORD
