Metadata-Version: 2.1
Name: unknown-fields
Version: 0.0.1a1
Summary: Wrapper to handle unknown parameters for dataclasses init
Author-email: haruna-dev <haruna-dev@proton.me>
Project-URL: Homepage, https://github.com/haruna-dev/unknown_fields
Project-URL: Bug Tracker, https://github.com/haruna-dev/unknown_fields/issues
Classifier: Programming Language :: Python :: 3
Classifier: License :: OSI Approved :: MIT License
Classifier: Operating System :: OS Independent
Requires-Python: >=3.7
License-File: LICENSE
